<annotation>
	<folder>images</folder>
	<filename>r1p00017o8171pnq407.jpg</filename>
	<path>P:\mask_mouth\images\r1p00017o8171pnq407.jpg</path>
	<source>
		<database>Unknown</database>
	</source>
	<size>
		<width>640</width>
		<height>959</height>
		<depth>3</depth>
	</size>
	<segmented>0</segmented>
	<object>
		<name>none</name>
		<pose>Unspecified</pose>
		<truncated>0</truncated>
		<difficult>0</difficult>
		<bndbox>
			<xmin>251</xmin>
			<ymin>180</ymin>
			<xmax>385</xmax>
			<ymax>278</ymax>
		</bndbox>
	</object>
</annotation>
