<annotation>
	<folder>images</folder>
	<filename>1477443223-1445746883.jpg</filename>
	<path>P:\mask_mouth\images\1477443223-1445746883.jpg</path>
	<source>
		<database>Unknown</database>
	</source>
	<size>
		<width>800</width>
		<height>527</height>
		<depth>3</depth>
	</size>
	<segmented>0</segmented>
	<object>
		<name>good</name>
		<pose>Unspecified</pose>
		<truncated>0</truncated>
		<difficult>0</difficult>
		<bndbox>
			<xmin>104</xmin>
			<ymin>198</ymin>
			<xmax>214</xmax>
			<ymax>314</ymax>
		</bndbox>
	</object>
	<object>
		<name>good</name>
		<pose>Unspecified</pose>
		<truncated>0</truncated>
		<difficult>0</difficult>
		<bndbox>
			<xmin>556</xmin>
			<ymin>188</ymin>
			<xmax>718</xmax>
			<ymax>360</ymax>
		</bndbox>
	</object>
</annotation>
