<annotation>
	<folder>images</folder>
	<filename>3060869_1_1.jpg</filename>
	<path>P:\mask_mouth\images\3060869_1_1.jpg</path>
	<source>
		<database>Unknown</database>
	</source>
	<size>
		<width>800</width>
		<height>534</height>
		<depth>3</depth>
	</size>
	<segmented>0</segmented>
	<object>
		<name>none</name>
		<pose>Unspecified</pose>
		<truncated>0</truncated>
		<difficult>0</difficult>
		<bndbox>
			<xmin>361</xmin>
			<ymin>107</ymin>
			<xmax>546</xmax>
			<ymax>324</ymax>
		</bndbox>
	</object>
	<object>
		<name>good</name>
		<pose>Unspecified</pose>
		<truncated>0</truncated>
		<difficult>0</difficult>
		<bndbox>
			<xmin>198</xmin>
			<ymin>173</ymin>
			<xmax>351</xmax>
			<ymax>330</ymax>
		</bndbox>
	</object>
	<object>
		<name>good</name>
		<pose>Unspecified</pose>
		<truncated>0</truncated>
		<difficult>0</difficult>
		<bndbox>
			<xmin>578</xmin>
			<ymin>198</ymin>
			<xmax>710</xmax>
			<ymax>465</ymax>
		</bndbox>
	</object>
</annotation>
